ensaio/__init__.py
ensaio/_fetchers.py
ensaio/_version.py
ensaio/_version_generated.py
ensaio/tests/__init__.py
ensaio/tests/test_fetchers.py
ensaio-0.7.0.dist-info/AUTHORS.md
ensaio-0.7.0.dist-info/LICENSE.txt
ensaio-0.7.0.dist-info/METADATA
ensaio-0.7.0.dist-info/WHEEL
ensaio-0.7.0.dist-info/top_level.txt
ensaio-0.7.0.dist-info/RECORD
