Metadata-Version: 2.2
Name: ensaio
Version: 0.7.0
Summary: Practice datasets to probe your code
Author-email: The Ensaio Developers <fatiandoaterra@protonmail.com>
Maintainer-email: Leonardo Uieda <leo@uieda.com>
License: BSD 3-Clause
Project-URL: Documentation, https://www.fatiando.org/ensaio
Project-URL: Changelog, https://www.fatiando.org/ensaio/latest/changes.html
Project-URL: Bug Tracker, https://github.com/fatiando/ensaio/issues
Project-URL: Source Code, https://github.com/fatiando/ensaio
Keywords: geophysics,geodesy,data
Classifier: Development Status :: 5 - Production/Stable
Classifier: License :: OSI Approved :: BSD License
Classifier: Operating System :: OS Independent
Classifier: Intended Audience :: Science/Research
Classifier: Intended Audience :: Developers
Classifier: Intended Audience :: Education
Classifier: Topic :: Scientific/Engineering
Classifier: Topic :: Software Development :: Libraries
Classifier: Programming Language :: Python
Classifier: Programming Language :: Python :: 3
Classifier: Programming Language :: Python :: 3.9
Classifier: Programming Language :: Python :: 3.10
Classifier: Programming Language :: Python :: 3.11
Classifier: Programming Language :: Python :: 3.12
Classifier: Programming Language :: Python :: 3.13
Requires-Python: >=3.9
License-File: LICENSE.txt
License-File: AUTHORS.md
Requires-Dist: pooch<2.0.0,>=1.5.0
